cisb/__init__.py
cisb/cli.py
recommendations/__init__.py
recommendations/gitlab/__init__.py
recommendations/gitlab/artifacts.py
recommendations/gitlab/build_pipelines.py
recommendations/gitlab/dependencies.py
recommendations/gitlab/deployments.py
recommendations/gitlab/source_code.py
services/__init__.py
services/common_utils.py
services/github_service.py
services/gitlab_service.py
cisb-0.1.0.dist-info/METADATA
cisb-0.1.0.dist-info/WHEEL
cisb-0.1.0.dist-info/entry_points.txt
cisb-0.1.0.dist-info/top_level.txt
cisb-0.1.0.dist-info/RECORD
