Metadata-Version: 2.1
Name: cisb
Version: 0.1.0
Summary: GitLab Security Compliance CLI
Keywords: GitLab,security,compliance,CIS benchmarks
Classifier: Programming Language :: Python :: 3
Classifier: License :: OSI Approved :: MIT License
Classifier: Operating System :: OS Independent
Requires-Python: >=3.7
Requires-Dist: aiohttp<4,>=3.10.5
Requires-Dist: aiohappyeyeballs>=2.3.0
Requires-Dist: aiosignal>=1.1.2
Requires-Dist: attrs>=17.3.0
Requires-Dist: frozenlist>=1.1.1
Requires-Dist: multidict<7.0,>=4.5
Requires-Dist: yarl<2.0,>=1.0
Requires-Dist: idna>=2.0
Requires-Dist: diskcache>=5.6.3
Requires-Dist: click>=8.1.7
Requires-Dist: requests<3,>=2.32.3
Requires-Dist: certifi>=2017.4.17
Requires-Dist: charset-normalizer<4,>=2
Requires-Dist: urllib3<3,>=1.21.1
Requires-Dist: python-dateutil>=2.9.0
Requires-Dist: six>=1.5
Requires-Dist: PyYAML>=6.0.2
Requires-Dist: setuptools>=75.1.0
Provides-Extra: dev
Requires-Dist: pytest; extra == "dev"
Requires-Dist: black; extra == "dev"
Requires-Dist: flake8; extra == "dev"
